backstabbr_api/__init__.py
backstabbr_api/backstabbr_api.py
backstabbr_bot/__init__.py
backstabbr_bot/backstabbr_bot.py
backstabbr_api-2.0.0.dist-info/LICENSE
backstabbr_api-2.0.0.dist-info/METADATA
backstabbr_api-2.0.0.dist-info/WHEEL
backstabbr_api-2.0.0.dist-info/top_level.txt
backstabbr_api-2.0.0.dist-info/RECORD
