Metadata-Version: 2.1
Name: backstabbr-api
Version: 2.0.0
Summary: Web-scraper API and Discord Bot for the online diplomacy program Backstabbr
Home-page: https://github.com/afkhurana/backstabbr_api
Author: Arjun Khurana
Author-email: afkhurana@gmail.com
License: MIT
Platform: UNKNOWN
Requires-Dist: discord.py
Requires-Dist: html5print
Requires-Dist: requests
